opcuawebclient/index.html
opcuawebclient/info.py
opcuawebclient/info.pyc
opcuawebclient/mainserver.py
opcuawebclient/mainserver.pyc
opcuawebclient/opcua-webclient
opcuawebclient/opcua-webclient.bat
opcuawebclient/wsserver.py
opcuawebclient/wsserver.pyc
opcuawebclient/__init__.py
opcuawebclient/__init__.pyc
opcuawebclient/__main__.py
opcuawebclient/static/fetch.js
opcuawebclient/static/irws.js
opcuawebclient/static/vue.js
opcuawebclient/static/vue.min.js
opcuawebclient/__pycache__/info.cpython-36.pyc
opcuawebclient/__pycache__/__init__.cpython-36.pyc
opcua_webclient-0.0.5.data/scripts/opcua-webclient
opcua_webclient-0.0.5.data/scripts/opcua-webclient.bat
opcua_webclient-0.0.5.dist-info/DESCRIPTION.rst
opcua_webclient-0.0.5.dist-info/METADATA
opcua_webclient-0.0.5.dist-info/metadata.json
opcua_webclient-0.0.5.dist-info/RECORD
opcua_webclient-0.0.5.dist-info/top_level.txt
opcua_webclient-0.0.5.dist-info/WHEEL
