Metadata-Version: 2.0
Name: opcua-webclient
Version: 0.0.5
Summary: A OPCUA web client, implemented by Python.
Home-page: https://github.com/sintrb/python-opcua-webclient
Author: sintrb
Author-email: sintrb@gmail.com
License: Apache
Keywords: OPC OPCUA WEB CLIENT
Platform: UNKNOWN
Classifier: Intended Audience :: Developers
Classifier: Operating System :: OS Independent
Classifier: Programming Language :: Python :: 2.7
Requires-Dist: tornado
Requires-Dist: freeopcua
